foxify_cli/__init__.py
foxify_cli/__main__.py
foxify_cli/config/__init__.py
foxify_cli/config/startup.py
foxify_cli/core/__init__.py
foxify_cli/core/argparser.py
foxify_cli/core/methods.py
foxify_cli/logger/__init__.py
foxify_cli-1.2.dist-info/LICENSE
foxify_cli-1.2.dist-info/METADATA
foxify_cli-1.2.dist-info/WHEEL
foxify_cli-1.2.dist-info/entry_points.txt
foxify_cli-1.2.dist-info/top_level.txt
foxify_cli-1.2.dist-info/zip-safe
foxify_cli-1.2.dist-info/RECORD
